{
  "title": "ஜம்பட்டா வீதியிலுள்ள இரசாயன களஞ்சியசாலையில் தீ",
  "content": "கொழும்பு – ஜம்பட்டா வீதியில் இரசாயனப் பொருட்கள் களஞ்சியப்படுத்தப்பட்டிருந்த நிலையத்தில் தீ பரவியுள்ளது.தீயை அணைப்பதற்காக 12 தீயணைப்பு வாகனங்கள் அனுப்பிவைக்கப்பட்டதாக கொழும்பு தீயணைப்புச் சேவை திணைக்களம் தெரிவித்துள்ளது.",
  "url": "https://www.newsfirst.lk/tamil/2022/02/27/%e0%ae%9c%e0%ae%ae%e0%af%8d%e0%ae%aa%e0%ae%9f%e0%af%8d%e0%ae%9f%e0%ae%be-%e0%ae%b5%e0%af%80%e0%ae%a4%e0%ae%bf%e0%ae%af%e0%ae%bf%e0%ae%b2%e0%af%81%e0%ae%b3%e0%af%8d%e0%ae%b3-%e0%ae%87%e0%ae%b0%e0%ae%9a/",
  "date": "2022-02-27",
  "category": "general"
}